pyruler/__init__.py
pyruler/errors.py
pyruler/linked_list.py
pyruler/pyruler.py
pyruler/rule.py
pyruler/ruleset.py
pyruler-0.12.0.dist-info/LICENSE
pyruler-0.12.0.dist-info/WHEEL
pyruler-0.12.0.dist-info/METADATA
pyruler-0.12.0.dist-info/RECORD
